.hgignore
CHANGES.txt
LICENSE.txt
README.txt
_version.py
distribute_setup.py
setup.cfg
setup.py
wplsync.py
wplsync/__init__.py
wplsync/_version.py
wplsync/wplsync.py
wplsync.egg-info/SOURCES.txt
wplsync/test/__init__.py
wplsync/test/__init__.py