Metadata-Version: 1.0
Name: wplsync
Version: 1.0.0a1
Summary: Python console script to synchronize media folders, using playlists as filter
Home-page: http://wplsync.googlecode.com/
Author: Martin Wendt
Author-email: wplsync@wwwendt.de
License: The MIT License
Keywords: playlist wpl folder sync
Platform: UNKNOWN
Classifier: Development Status :: 3 - Alpha
Classifier: Environment :: Console
Classifier: Intended Audience :: End Users/Desktop
Classifier: License :: OSI Approved :: MIT License
Classifier: Natural Language :: English
Classifier: Operating System :: OS Independent
Classifier: Programming Language :: Python :: 2
